auglib/__init__.py
auglib/core/__init__.py
auglib/core/cache.py
auglib/core/config.py
auglib/core/conftest.py
auglib/core/interface.py
auglib/core/observe.py
auglib/core/resolver.py
auglib/core/seed.py
auglib/core/time.py
auglib/core/transform.py
auglib/core/utils.py
auglib/core/bin/libSoundTouch.so.1
auglib/core/bin/libcauglib.so
auglib/core/bin/libopencore-amrnb.so.0
auglib/observe/__init__.py
auglib/transform/__init__.py
auglib/utils/__init__.py
auglib-1.0.4.dist-info/LICENSE
auglib-1.0.4.dist-info/METADATA
auglib-1.0.4.dist-info/WHEEL
auglib-1.0.4.dist-info/top_level.txt
auglib-1.0.4.dist-info/RECORD
