Metadata-Version: 2.1
Name: auglib
Version: 1.0.4
Summary: Audio augmentations
Author: Johannes Wagner, Andrea Crespi, Andreas Triantafyllopoulos, BahaEddine Abrougui
Author-email: Hagen Wierstorf <hwierstorf@audeering.com>, Anna Derington <aderington@audeering.com>
License: MIT License
Project-URL: repository, https://github.com/audeering/auglib/
Project-URL: documentation, https://audeering.github.io/auglib/
Keywords: audio,data,tools,data augmentation,machine learning
Classifier: Development Status :: 5 - Production/Stable
Classifier: Intended Audience :: Science/Research
Classifier: Intended Audience :: Developers
Classifier: License :: OSI Approved :: MIT License
Classifier: Operating System :: OS Independent
Classifier: Programming Language :: Python
Classifier: Programming Language :: Python :: 3
Classifier: Programming Language :: Python :: 3.11
Classifier: Programming Language :: Python :: 3.10
Classifier: Programming Language :: Python :: 3.9
Classifier: Topic :: Scientific/Engineering
License-File: LICENSE
Requires-Dist: audeer >=2.0.0
Requires-Dist: audformat >=1.1.0
Requires-Dist: audinterface >=1.0.4
Requires-Dist: audmath >=1.3.0
Requires-Dist: audobject >=0.7.6
Requires-Dist: scipy
